sorm_location_asn1/__init__.py
sorm_location_asn1/base_location.py
sorm_location_asn1/gsm_location.py
sorm_location_asn1/lte_location.py
sorm_location_asn1/schema.py
sorm_location_asn1-0.7.1.dist-info/LICENSE.txt
sorm_location_asn1-0.7.1.dist-info/METADATA
sorm_location_asn1-0.7.1.dist-info/WHEEL
sorm_location_asn1-0.7.1.dist-info/top_level.txt
sorm_location_asn1-0.7.1.dist-info/RECORD
