Metadata-Version: 2.1
Name: sorm-location-asn1
Version: 0.7.1
Summary: Asn.1 representation for sorm645 location field
Home-page: https://github.com/chabErch/sorm_location_asn1
Author: chabErch
Author-email: chabErch@yandex.ru
License: UNKNOWN
Platform: UNKNOWN
Classifier: Development Status :: 3 - Alpha
Classifier: License :: OSI Approved :: MIT License
Classifier: Natural Language :: Russian
Classifier: Programming Language :: Python :: 3
Requires-Dist: pyderasn (>=8.1)
